pyoifits/__init__.py
pyoifits/coo.py
pyoifits/fitsutils.py
pyoifits/oifits.py
pyoifits/utils.py
pyoifits/hdu/__init__.py
pyoifits/hdu/array.py
pyoifits/hdu/base.py
pyoifits/hdu/corr.py
pyoifits/hdu/data.py
pyoifits/hdu/flux.py
pyoifits/hdu/inspol.py
pyoifits/hdu/primary.py
pyoifits/hdu/referenced.py
pyoifits/hdu/t2.py
pyoifits/hdu/t3.py
pyoifits/hdu/table.py
pyoifits/hdu/target.py
pyoifits/hdu/vis.py
pyoifits/hdu/vis2.py
pyoifits/hdu/wavelength.py
pyoifits-0.4.10.dist-info/LICENCE.txt
pyoifits-0.4.10.dist-info/METADATA
pyoifits-0.4.10.dist-info/WHEEL
pyoifits-0.4.10.dist-info/top_level.txt
pyoifits-0.4.10.dist-info/RECORD
