Metadata-Version: 2.1
Name: pyoifits
Version: 0.4.10
Summary: OIFITS (Data Exchange Standard for Optical Interferometry, A&A 597, A8, 2017)
Home-page: UNKNOWN
Author: Régis Lachaume
Author-email: regis.lachaume@gmail.com
License: LICENSE.txt
Platform: UNKNOWN
Classifier: Programming Language :: Python :: 3
Classifier: Development Status :: 3 - Alpha
Classifier: Operating System :: OS Independent
Classifier: Intended Audience :: Science/Research
Classifier: Topic :: Scientific/Engineering :: Astronomy
Classifier: License :: Public Domain
Requires-Python: >=3.8
License-File: LICENCE.txt
Requires-Dist: astropy (>=4.0)
Requires-Dist: numpy (>=1.17)
Requires-Dist: scipy (>=1.5)
Requires-Dist: astroquery (>=0.4)
